poorajenny/__init__.py
poorajenny/poora.py
JennyPoora-0.1.dist-info/METADATA
JennyPoora-0.1.dist-info/WHEEL
JennyPoora-0.1.dist-info/top_level.txt
JennyPoora-0.1.dist-info/RECORD
